gptclass/__init__.py
gptclass/function_utils.py
gptclass/gpt_class.py
gptclass-0.4.0.dist-info/LICENSE
gptclass-0.4.0.dist-info/METADATA
gptclass-0.4.0.dist-info/WHEEL
gptclass-0.4.0.dist-info/RECORD
