Metadata-Version: 2.1
Name: gptclass
Version: 0.4.0
Summary: A Python class that does what you need
Home-page: https://github.com/jaume-ferrarons/GPTClass
License: MIT
Keywords: gpt,openai,code-generations
Author: Jaume Ferrarons
Author-email: jaume.ferrarons@gmail.com
Requires-Python: >=3.8.1,<4.0
Classifier: License :: OSI Approved :: MIT License
Classifier: Programming Language :: Python :: 3
Classifier: Programming Language :: Python :: 3.9
Classifier: Programming Language :: Python :: 3.10
Classifier: Programming Language :: Python :: 3.11
Requires-Dist: diskcache (>=5.4.0,<6.0.0)
Requires-Dist: openai (>=0.27.0,<0.28.0)
Project-URL: Repository, https://github.com/jaume-ferrarons/GPTClass
